odoo/addons/base_import_async/README.rst
odoo/addons/base_import_async/__init__.py
odoo/addons/base_import_async/__manifest__.py
odoo/addons/base_import_async/data/queue_job_function_data.xml
odoo/addons/base_import_async/i18n/base_import_async.pot
odoo/addons/base_import_async/i18n/es.po
odoo/addons/base_import_async/i18n/it.po
odoo/addons/base_import_async/i18n/nl.po
odoo/addons/base_import_async/i18n/tr.po
odoo/addons/base_import_async/models/__init__.py
odoo/addons/base_import_async/models/base_import_import.py
odoo/addons/base_import_async/models/queue_job.py
odoo/addons/base_import_async/readme/CONTRIBUTORS.md
odoo/addons/base_import_async/readme/CREDITS.md
odoo/addons/base_import_async/readme/DESCRIPTION.md
odoo/addons/base_import_async/readme/HISTORY.md
odoo/addons/base_import_async/readme/ROADMAP.md
odoo/addons/base_import_async/readme/USAGE.md
odoo/addons/base_import_async/static/description/icon.png
odoo/addons/base_import_async/static/description/index.html
odoo/addons/base_import_async/static/src/js/import_model.esm.js
odoo/addons/base_import_async/static/src/xml/import_data_sidepanel.xml
odoo/addons/base_import_async/tests/__init__.py
odoo/addons/base_import_async/tests/test_base_import_import.py
odoo_addon_base_import_async-18.0.1.0.0.6.dist-info/METADATA
odoo_addon_base_import_async-18.0.1.0.0.6.dist-info/WHEEL
odoo_addon_base_import_async-18.0.1.0.0.6.dist-info/top_level.txt
odoo_addon_base_import_async-18.0.1.0.0.6.dist-info/RECORD
